poverse/__init__.py
poverse/cli.py
poverse/exceptions.py
poverse-0.1.2.dist-info/entry_points.txt
poverse-0.1.2.dist-info/LICENSE
poverse-0.1.2.dist-info/WHEEL
poverse-0.1.2.dist-info/METADATA
poverse-0.1.2.dist-info/RECORD
