Metadata-Version: 2.1
Name: poverse
Version: 0.1.2
Summary: Get the installed version of dependency within poetry.lock file
Home-page: https://github.com/JoelClemence/poverse
License: MIT
Keywords: Poetry,dependencies
Author: Joel Clemence
Requires-Python: >=3.7,<4.0
Classifier: Development Status :: 3 - Alpha
Classifier: Intended Audience :: Developers
Classifier: Intended Audience :: Science/Research
Classifier: License :: OSI Approved :: MIT License
Classifier: Natural Language :: English
Classifier: Programming Language :: Python :: 3
Classifier: Programming Language :: Python :: 3.7
Classifier: Programming Language :: Python :: 3.8
Classifier: Programming Language :: Python :: 3.9
Classifier: Topic :: Software Development :: Build Tools
Classifier: Typing :: Typed
Requires-Dist: click (>=8.0.1,<9.0.0)
Requires-Dist: toml (>=0.10.2,<0.11.0)
Project-URL: Bug Tracker, https://github.com/JoelClemence/poverse/issues
Project-URL: Repository, https://github.com/JoelClemence/poverse
